{
    "type" : "container",
    "sub_type" : "configuration",
    "id" : "pt.hive.colony.configuration.development.main_service_pop",
    "configuration_id" : "pt.hive.colony.plugins.resources.resource_manager",
    "name" : "Main Service Pop Development Configuration",
    "short_name" : "Main Service Pop Development",
    "description" : "The main service pop configuration for the development profile",
    "version" : "1.0.0",
    "author" : "Hive Solutions Lda. <development@hive.pt>",
    "dependencies" : [],
    "resources" : [
            "configuration/main_service_pop/run_mode/development/configuration.py",
            "configuration/main_service_pop/run_mode/development/resources.xml"],
    "extra_resources" : ["configuration/main_service_pop/run_mode/development/configuration.pyc"]
}
